py_pixel_art_snake_package/__init__.py
py_pixel_art_snake_package/py_pixel_art_snake/Score.csv
py_pixel_art_snake_package/py_pixel_art_snake/Snake_menu.jpg
py_pixel_art_snake_package/py_pixel_art_snake/__init__.py
py_pixel_art_snake_package/py_pixel_art_snake/apple.png
py_pixel_art_snake_package/py_pixel_art_snake/appleaswd.png
py_pixel_art_snake_package/py_pixel_art_snake/button.py
py_pixel_art_snake_package/py_pixel_art_snake/cabeça_cobra.png
py_pixel_art_snake_package/py_pixel_art_snake/cabeça_cobra1.jpg
py_pixel_art_snake_package/py_pixel_art_snake/cabeça_cobra_down.png
py_pixel_art_snake_package/py_pixel_art_snake/cabeça_cobra_down_eating.png
py_pixel_art_snake_package/py_pixel_art_snake/cabeça_cobra_left.png
py_pixel_art_snake_package/py_pixel_art_snake/cabeça_cobra_left_eating.png
py_pixel_art_snake_package/py_pixel_art_snake/cabeça_cobra_right.png
py_pixel_art_snake_package/py_pixel_art_snake/cabeça_cobra_right_eating.png
py_pixel_art_snake_package/py_pixel_art_snake/cabeça_cobra_top.png
py_pixel_art_snake_package/py_pixel_art_snake/cabeça_cobra_top_eating.png
py_pixel_art_snake_package/py_pixel_art_snake/cherry.jpeg
py_pixel_art_snake_package/py_pixel_art_snake/cobra_gomo.png
py_pixel_art_snake_package/py_pixel_art_snake/cobra_gomo_down.png
py_pixel_art_snake_package/py_pixel_art_snake/cobra_gomo_top.png
py_pixel_art_snake_package/py_pixel_art_snake/collision.py
py_pixel_art_snake_package/py_pixel_art_snake/config.csv
py_pixel_art_snake_package/py_pixel_art_snake/config_state.py
py_pixel_art_snake_package/py_pixel_art_snake/direct_to_go.py
py_pixel_art_snake_package/py_pixel_art_snake/dist_to_go.py
py_pixel_art_snake_package/py_pixel_art_snake/escudo.jpeg
py_pixel_art_snake_package/py_pixel_art_snake/exit.png
py_pixel_art_snake_package/py_pixel_art_snake/freesansbold.ttf
py_pixel_art_snake_package/py_pixel_art_snake/game over.png
py_pixel_art_snake_package/py_pixel_art_snake/game_inputs.py
py_pixel_art_snake_package/py_pixel_art_snake/game_over.jpeg
py_pixel_art_snake_package-0.0.1.dist-info/METADATA
py_pixel_art_snake_package-0.0.1.dist-info/WHEEL
py_pixel_art_snake_package-0.0.1.dist-info/top_level.txt
py_pixel_art_snake_package-0.0.1.dist-info/RECORD
