Metadata-Version: 2.1
Name: py-pixel-art-snake-package
Version: 0.0.1
Summary: Mode used to play snake game in python with pixel art
Home-page: https://github.com/Calima94/dio_snake_pkg_create.git
Author: Calins_e_Marcosvinisilv
Author-email: caiolima2000@hotmail.com
License: UNKNOWN
Platform: UNKNOWN
Requires-Python: >=3.7
Requires-Dist: pygame
Requires-Dist: pygame-gui
Requires-Dist: pandas
Requires-Dist: numpy
Requires-Dist: matplotlib
Requires-Dist: setuptools
